discord_sls/__init__.py
discord_sls/app_client.py
discord_sls/interaction.py
discord_sls/lambda_bot.py
discord_sls-0.4.0.dist-info/METADATA
discord_sls-0.4.0.dist-info/WHEEL
discord_sls-0.4.0.dist-info/entry_points.txt
discord_sls-0.4.0.dist-info/top_level.txt
discord_sls-0.4.0.dist-info/RECORD
