Metadata-Version: 2.1
Name: discord-sls
Version: 0.4.0
Summary: For building serverless discord bots
Home-page: https://github.com/beverts312/discord-sls
Author: Bailey Everts
Author-email: bailey@evertsenterprises.com
License: MIT
Platform: UNKNOWN
Requires-Dist: requests
Requires-Dist: PyNaCl
Requires-Dist: PyYAML
